latex_to_myst/__init__.py
latex_to_myst/cli.py
latex_to_myst/directive.py
latex_to_myst/figures.py
latex_to_myst/latex_math.py
latex_to_myst/macros.tex
latex_to_myst/main.py
latex_to_myst/pygments.theme
latex_to_myst-0.0.1.dist-info/AUTHORS.rst
latex_to_myst-0.0.1.dist-info/LICENSE
latex_to_myst-0.0.1.dist-info/METADATA
latex_to_myst-0.0.1.dist-info/WHEEL
latex_to_myst-0.0.1.dist-info/entry_points.txt
latex_to_myst-0.0.1.dist-info/top_level.txt
latex_to_myst-0.0.1.dist-info/RECORD
