Metadata-Version: 2.1
Name: latex-to-myst
Version: 0.0.1
Summary: LaTeX to MyST converter
Home-page: https://github.com/TK-21st/latex-to-myst
Author: Tingkai Liu
Author-email: tingkai.liu.21st@gmail.com
License: BSD 3-Clause license
Keywords: latex_to_myst
Platform: UNKNOWN
Classifier: Development Status :: 2 - Pre-Alpha
Classifier: Intended Audience :: Developers
Classifier: License :: OSI Approved :: BSD License
Classifier: Natural Language :: English
Classifier: Programming Language :: Python :: 3
Classifier: Programming Language :: Python :: 3.7
Classifier: Programming Language :: Python :: 3.8
Classifier: Programming Language :: Python :: 3.9
Requires-Python: >=3.7
License-File: LICENSE
License-File: AUTHORS.rst
Requires-Dist: panflute (>=2.1)
Requires-Dist: numpy (>=1.20)
